jinja2static/__init__.py
jinja2static/__main__.py
jinja2static/assets.py
jinja2static/config.py
jinja2static/files.py
jinja2static/logger.py
jinja2static/server.py
jinja2static/templates.py
jinja2static/watcher.py
jinja2static/data/__init__.py
jinja2static/data/helpers.py
jinja2static/init/__init__.py
jinja2static/init/__main__.py
jinja2static-0.4.0.dist-info/licenses/LICENSE
jinja2static-0.4.0.dist-info/METADATA
jinja2static-0.4.0.dist-info/WHEEL
jinja2static-0.4.0.dist-info/entry_points.txt
jinja2static-0.4.0.dist-info/top_level.txt
jinja2static-0.4.0.dist-info/RECORD
