Metadata-Version: 2.4
Name: jinja2static
Version: 0.4.0
Summary: A simple static file generator based off of the Jinja templating language.
Author-email: Michael Airola <me@michaelairola.com>
License: MIT License
Classifier: Programming Language :: Python :: 3
Classifier: License :: OSI Approved :: MIT License
Classifier: Operating System :: OS Independent
Requires-Python: >=3.10
License-File: LICENSE
Requires-Dist: Jinja2>=3.1.6
Requires-Dist: PyYaml>=6.0.3
Provides-Extra: dev
Requires-Dist: pytest; extra == "dev"
Requires-Dist: ruff; extra == "dev"
Requires-Dist: twine; extra == "dev"
Requires-Dist: build; extra == "dev"
Dynamic: license-file
